famews/__init__.py
famews/pipeline.py
famews-0.1.2.dist-info/LICENSE
famews-0.1.2.dist-info/METADATA
famews-0.1.2.dist-info/WHEEL
famews-0.1.2.dist-info/top_level.txt
famews-0.1.2.dist-info/RECORD
