Metadata-Version: 2.1
Name: famews
Version: 0.1.2
Summary: FAMEWS: A Fairness Auditing tool for Medical Early-Warning Systems
Home-page: https://github.com/ratschlab/famews
Author: Marine Hoche, Olga Mineeva, Manuel Burger, Alessandro Blasimme, Gunnar Rätsch
License: MIT License
Keywords: Fairness,Machine Learning,Early-Warning System,Clinical Applications
Classifier: Programming Language :: Python :: 3
Classifier: Operating System :: OS Independent
Requires-Python: >=3.9
License-File: LICENSE
Requires-Dist: pandas
Requires-Dist: numpy ==1.23
Requires-Dist: pandas <2.0
Requires-Dist: scikit-learn >=1.2.0
Requires-Dist: jupyter
Requires-Dist: seaborn >=0.12.2
Requires-Dist: matplotlib >=3.6.2
Requires-Dist: pytest ==7.1.2
Requires-Dist: mypy ==0.981
Requires-Dist: tqdm >=4.64
Requires-Dist: pyarrow >=8.0.0
Requires-Dist: black ==22.6.0
Requires-Dist: isort ==5.9.3
Requires-Dist: gin-config >=0.5.0
Requires-Dist: coolname >=2.2.0
Requires-Dist: plotly >=5.9.0
Requires-Dist: shap >=0.41.0
Requires-Dist: setuptools
Requires-Dist: wheel
Requires-Dist: twine
Requires-Dist: pathos >=0.2.9
Requires-Dist: coloredlogs >=15.0
Requires-Dist: types-PyYAML
Requires-Dist: reportlab >=4.0.4
Requires-Dist: rbo >=0.1.3
